<annotation>
	<folder>final_folder</folder>
	<filename>coin500_o2_235_0_706.jpg</filename>
	<path>final_folder/coin500_o2_235_0_706.jpg</path>
	<source>
		<database>Unknown</database>
	</source>
	<size>
		<width>1920</width>
		<height>1080</height>
		<depth>3</depth>
	</size>
	<segmented>0</segmented>
	<object>
		<name>500 Yen</name>
		<pose>Unspecified</pose>
		<truncated>0</truncated>
		<difficult>0</difficult>
		<bndbox>
			<xmin>802</xmin>
			<ymin>758</ymin>
			<xmax>1038</xmax>
			<ymax>997</ymax>
		</bndbox>
	</object>
</annotation>
