<annotation>
	<folder>final_folder</folder>
	<filename>coin50_019zoom_0_2132.jpg</filename>
	<path>final_folder/coin50_019zoom_0_2132.jpg</path>
	<source>
		<database>Unknown</database>
	</source>
	<size>
		<width>1920</width>
		<height>1080</height>
		<depth>3</depth>
	</size>
	<segmented>0</segmented>
	<object>
		<name>50 Yen</name>
		<pose>Unspecified</pose>
		<truncated>0</truncated>
		<difficult>0</difficult>
		<bndbox>
			<xmin>1143</xmin>
			<ymin>131</ymin>
			<xmax>1455</xmax>
			<ymax>358</ymax>
		</bndbox>
	</object>
</annotation>
